aimhub_license/__init__.py
aimhub_license/utils.cpython-39-x86_64-linux-gnu.so
aimhub_license-0.7.0.dist-info/METADATA
aimhub_license-0.7.0.dist-info/WHEEL
aimhub_license-0.7.0.dist-info/top_level.txt
aimhub_license-0.7.0.dist-info/RECORD
