Metadata-Version: 2.4
Name: aimhub-license
Version: 0.7.0
Summary: License validation module for AimHub deployments
Requires-Python: >=3.9,<3.10
Requires-Dist: redis==4.6.0
Requires-Dist: cachetools==5.3.3
Dynamic: requires-dist
Dynamic: requires-python
Dynamic: summary
